LICENSE
MANIFEST.in
README.md
pyproject.toml
setup.py
cuquantum/densitymat/jax/__init__.py
cuquantum/densitymat/jax/operator_action.py
cuquantum/densitymat/jax/utils.py
cuquantum/densitymat/jax/cppsrc/CMakeLists.txt
cuquantum/densitymat/jax/cppsrc/cudensitymat_jax.cpp
cuquantum/densitymat/jax/cppsrc/cudensitymat_jax.h
cuquantum/densitymat/jax/cppsrc/pybind.cpp
cuquantum/densitymat/jax/cppsrc/utils.h
cuquantum/densitymat/jax/pysrc/__init__.py
cuquantum/densitymat/jax/pysrc/base.py
cuquantum/densitymat/jax/pysrc/context.py
cuquantum/densitymat/jax/pysrc/elementary_operator.py
cuquantum/densitymat/jax/pysrc/matrix_operator.py
cuquantum/densitymat/jax/pysrc/operator.py
cuquantum/densitymat/jax/pysrc/operator_action_prim.py
cuquantum/densitymat/jax/pysrc/operator_term.py
cuquantum_python_jax.egg-info/PKG-INFO
cuquantum_python_jax.egg-info/SOURCES.txt
cuquantum_python_jax.egg-info/dependency_links.txt
cuquantum_python_jax.egg-info/not-zip-safe
cuquantum_python_jax.egg-info/requires.txt
cuquantum_python_jax.egg-info/top_level.txt