Metadata-Version: 2.4
Name: cuquantum-python-jax
Version: 0.0.4
Summary: NVIDIA cuQuantum Python JAX
Home-page: https://developer.nvidia.com/cuquantum-sdk
Author: NVIDIA Corporation
Author-email: cuquantum-python@nvidia.com
License: BSD-3-Clause
Classifier: Development Status :: 5 - Production/Stable
Classifier: Operating System :: POSIX :: Linux
Classifier: Topic :: Education
Classifier: Topic :: Scientific/Engineering
Classifier: Programming Language :: Python :: 3 :: Only
Classifier: Programming Language :: Python :: 3.11
Classifier: Programming Language :: Python :: 3.12
Classifier: Programming Language :: Python :: 3.13
Classifier: Programming Language :: Python :: Implementation :: CPython
Classifier: Environment :: GPU :: NVIDIA CUDA
Classifier: Environment :: GPU :: NVIDIA CUDA :: 12
Requires-Python: >=3.11.0
License-File: LICENSE
Requires-Dist: pybind11
Requires-Dist: cuquantum-python-cu12~=26.1.0
Requires-Dist: jax[cuda12-local]<0.7,>=0.5
Dynamic: author
Dynamic: author-email
Dynamic: classifier
Dynamic: description
Dynamic: description-content-type
Dynamic: home-page
Dynamic: license
Dynamic: license-file
Dynamic: requires-dist
Dynamic: requires-python
Dynamic: summary
